{
    "AIPawn_Base_Female_C": "AI Player",
    "AIPawn_Base_Male_C": "AI Player",
    "AirBoat_V2_C": "Vehicle Damage",
    "AquaRail_A_01_C": "Vehicle Damage",
    "AquaRail_A_02_C": "Vehicle Damage",
    "AquaRail_A_03_C": "Vehicle Damage",
    "BP_ATV_C": "Vehicle Damage",
    "BP_BRDM_C": "Vehicle Damage",
    "BP_Bicycle_C": "Vehicle Damage",
    "BP_CoupeRB_C": "Vehicle Damage",
    "BP_DO_Circle_Train_Merged_C": "Train Damage",
    "BP_DO_Line_Train_Dino_Merged_C": "Train Damage",
    "BP_DO_Line_Train_Merged_C": "Train Damage",
    "BP_Dirtbike_C": "Vehicle Damage",
    "BP_DronePackage_Projectile_C": "Drone",
    "BP_Eragel_CargoShip01_C": "Ferry Damage",
    "BP_FakeLootProj_AmmoBox_C": "Loot Truck",
    "BP_FakeLootProj_MilitaryCrate_C": "Loot Truck",
    "BP_FireEffectController_C": "Molotov Damage",
    "BP_FireEffectController_JerryCan_C": "Molotov Damage",
    "BP_Helicopter_C": "AI Player",
    "BP_IncendiaryDebuff_C": "Burn",
    "BP_JerryCanFireDebuff_C": "Burn",
    "BP_JerryCan_FuelPuddle_C": "Burn",
    "BP_KillTruck_C": "Kill Truck",
    "BP_LootTruck_C": "Loot Truck",
    "BP_M_Rony_A_01_C": "Vehicle Damage",
    "BP_M_Rony_A_02_C": "Vehicle Damage",
    "BP_M_Rony_A_03_C": "Vehicle Damage",
    "BP_Mirado_A_02_C": "Vehicle Damage",
    "BP_Mirado_A_03_Esports_C": "Vehicle Damage",
    "BP_Mirado_Open_03_C": "Vehicle Damage",
    "BP_Mirado_Open_04_C": "Vehicle Damage",
    "BP_Mirado_Open_05_C": "Vehicle Damage",
    "BP_MolotovFireDebuff_C": "Molotov Fire Damage",
    "BP_Motorbike_04_C": "Vehicle Damage",
    "BP_Motorbike_04_Desert_C": "Vehicle Damage",
    "BP_Motorbike_04_SideCar_C": "Vehicle Damage",
    "BP_Motorbike_04_SideCar_Desert_C": "Vehicle Damage",
    "BP_Motorbike_Solitario_C": "Vehicle Damage",
    "BP_Motorglider_C": "UAF Damage",
    "BP_Motorglider_Green_C": "UAF Damage",
    "BP_Niva_01_C": "Vehicle Damage",
    "BP_Niva_02_C": "Vehicle Damage",
    "BP_Niva_03_C": "Vehicle Damage",
    "BP_Niva_04_C": "Vehicle Damage",
    "BP_Niva_05_C": "Vehicle Damage",
    "BP_Niva_06_C": "Vehicle Damage",
    "BP_Niva_07_C": "Vehicle Damage",
    "BP_PickupTruck_A_01_C": "Vehicle Damage",
    "BP_PickupTruck_A_02_C": "Vehicle Damage",
    "BP_PickupTruck_A_03_C": "Vehicle Damage",
    "BP_PickupTruck_A_04_C": "Vehicle Damage",
    "BP_PickupTruck_A_05_C": "Vehicle Damage",
    "BP_PickupTruck_A_esports_C": "Vehicle Damage",
    "BP_PickupTruck_B_01_C": "Vehicle Damage",
    "BP_PickupTruck_B_02_C": "Vehicle Damage",
    "BP_PickupTruck_B_03_C": "Vehicle Damage",
    "BP_PickupTruck_B_04_C": "Vehicle Damage",
    "BP_PickupTruck_B_05_C": "Vehicle Damage",
    "BP_Pillar_Car_C": "Vehicle Damage",
    "BP_PonyCoupe_C": "Vehicle Damage",
    "BP_Porter_C": "Vehicle Damage",
    "BP_Scooter_01_A_C": "Vehicle Damage",
    "BP_Scooter_02_A_C": "Vehicle Damage",
    "BP_Scooter_03_A_C": "Vehicle Damage",
    "BP_Scooter_04_A_C": "Vehicle Damage",
    "BP_Snowbike_01_C": "Vehicle Damage",
    "BP_Snowbike_02_C": "Vehicle Damage",
    "BP_Snowmobile_01_C": "Vehicle Damage",
    "BP_Snowmobile_02_C": "Vehicle Damage",
    "BP_Snowmobile_03_C": "Vehicle Damage",
    "BP_Spiketrap_C": "Spike Trap",
    "BP_TslGasPump_C": "Gas Pump",
    "BP_TukTukTuk_A_01_C": "Vehicle Damage",
    "BP_TukTukTuk_A_02_C": "Vehicle Damage",
    "BP_TukTukTuk_A_03_C": "Vehicle Damage",
    "BP_Van_A_01_C": "Vehicle Damage",
    "BP_Van_A_02_C": "Vehicle Damage",
    "BP_Van_A_03_C": "Vehicle Damage",
    "BattleRoyaleModeController_Chimera_C": "Bluezone",
    "BattleRoyaleModeController_Def_C": "Bluezone",
    "BattleRoyaleModeController_Desert_C": "Bluezone",
    "BattleRoyaleModeController_DihorOtok_C": "Bluezone",
    "BattleRoyaleModeController_Heaven_C": "Bluezone",
    "BattleRoyaleModeController_Kiki_C": "Bluezone",
    "BattleRoyaleModeController_Savage_C": "Bluezone",
    "BattleRoyaleModeController_Summerland_C": "Bluezone",
    "BattleRoyaleModeController_Tiger_C": "Bluezone",
    "BlackZoneController_Def_C": "Blackzone",
    "Bluezonebomb_EffectActor_C": "Grenade Explosion Damage",
    "Boat_PG117_C": "PG-117",
    "Buff_DecreaseBreathInApnea_C": "Drowning",
    "Buggy_A_01_C": "Vehicle Damage",
    "Buggy_A_02_C": "Vehicle Damage",
    "Buggy_A_03_C": "Vehicle Damage",
    "Buggy_A_04_C": "Vehicle Damage",
    "Buggy_A_05_C": "Vehicle Damage",
    "Buggy_A_06_C": "Vehicle Damage",
    "Carepackage_Container_C": "Care Package",
    "Dacia_A_01_v2_C": "Vehicle Damage",
    "Dacia_A_01_v2_snow_C": "Vehicle Damage",
    "Dacia_A_02_v2_C": "Vehicle Damage",
    "Dacia_A_03_v2_C": "Vehicle Damage",
    "Dacia_A_03_v2_Esports_C": "Vehicle Damage",
    "Dacia_A_04_v2_C": "Vehicle Damage",
    "DroppedItemGroup": "Object Fragments",
    "EmergencyAircraft_Tiger_C": "Emergency Aircraft",
    "Jerrycan": "Jerrycan",
    "JerrycanFire": "Jerrycan Fire",
    "Lava": "Lava",
    "Mortar_Projectile_C": "Mortar Explosion",
    "None": "None",
    "PG117_A_01_C": "Vehicle Damage",
    "PanzerFaust100M_Projectile_C": "Panzerfaust Damage",
    "PlayerFemale_A_C": "Punch Damage",
    "PlayerMale_A_C": "Punch Damage",
    "ProjC4_C": "C4 Explosion Damage",
    "ProjGrenade_C": "Grenade Explosion Damage",
    "ProjIncendiary_C": "Molotov Damage",
    "ProjMolotov_C": "Molotov Damage",
    "ProjMolotov_DamageField_Direct_C": "Molotov Damage",
    "ProjStickyGrenade_C": "C4 Explosion Damage",
    "RacingDestructiblePropaneTankActor_C": "Molotov Damage",
    "RacingModeContorller_Desert_C": "Bluezone",
    "RedZoneBomb_C": "Redzone",
    "RedZoneBombingField": "Redzone",
    "RedZoneBombingField_Def_C": "Redzone",
    "TslDestructibleSurfaceManager": "Destructible Surface",
    "TslPainCausingVolume": "Lava",
    "Uaz_A_01_C": "Vehicle Damage",
    "Uaz_Armored_C": "Vehicle Damage",
    "Uaz_B_01_C": "Vehicle Damage",
    "Uaz_B_01_esports_C": "Vehicle Damage",
    "Uaz_C_01_C": "Vehicle Damage",
    "UltAIPawn_Base_Female_C": "Punch Damage",
    "UltAIPawn_Base_Male_C": "Punch Damage",
    "WeapACE32_C": "Gun Damage",
    "WeapAK47_C": "Gun Damage",
    "WeapAUG_C": "Gun Damage",
    "WeapAWM_C": "Gun Damage",
    "WeapBerreta686_C": "Gun Damage",
    "WeapBerylM762_C": "Gun Damage",
    "WeapBizonPP19_C": "Gun Damage",
    "WeapCowbarProjectile_C": "Crowbar Projectile",
    "WeapCowbar_C": "Crowbar",
    "WeapCrossbow_1_C": "Crossbow Damage",
    "WeapDP12_C": "Gun Damage",
    "WeapDP28_C": "Gun Damage",
    "WeapDesertEagle_C": "Gun Damage",
    "WeapDuncansHK416_C": "Gun Damage",
    "WeapFNFal_C": "Gun Damage",
    "WeapG18_C": "Gun Damage",
    "WeapG36C_C": "Gun Damage",
    "WeapGroza_C": "Gun Damage",
    "WeapHK416_C": "Gun Damage",
    "WeapJuliesKar98k_C": "Gun Damage",
    "WeapK2_C": "Gun Damage",
    "WeapKar98k_C": "Gun Damage",
    "WeapL6_C": "Gun Damage",
    "WeapLunchmeatsAK47_C": "Gun Damage",
    "WeapM16A4_C": "Gun Damage",
    "WeapM1911_C": "Gun Damage",
    "WeapM249_C": "Gun Damage",
    "WeapM24_C": "Gun Damage",
    "WeapM9_C": "Gun Damage",
    "WeapMG3_C": "Gun Damage",
    "WeapMP5K_C": "Gun Damage",
    "WeapMP9_C": "Gun Damage",
    "WeapMacheteProjectile_C": "Machete Projectile",
    "WeapMachete_C": "Machete",
    "WeapMadsQBU88_C": "Gun Damage",
    "WeapMini14_C": "Gun Damage",
    "WeapMk12_C": "Gun Damage",
    "WeapMk14_C": "Gun Damage",
    "WeapMk47Mutant_C": "Gun Damage",
    "WeapMosinNagant_C": "Gun Damage",
    "WeapNagantM1895_C": "Gun Damage",
    "WeapOriginS12_C": "Gun Damage",
    "WeapP90_C": "Gun Damage",
    "WeapPanProjectile_C": "Pan Projectile",
    "WeapPan_C": "Pan",
    "WeapPanzerFaust100M1_C": "Panzerfaust Damage",
    "WeapQBU88_C": "Gun Damage",
    "WeapQBZ95_C": "Gun Damage",
    "WeapRhino_C": "Gun Damage",
    "WeapSCAR-L_C": "Gun Damage",
    "WeapSKS_C": "Gun Damage",
    "WeapSaiga12_C": "Gun Damage",
    "WeapSawnoff_C": "Gun Damage",
    "WeapSickleProjectile_C": "Sickle Projectile",
    "WeapSickle_C": "Sickle",
    "WeapThompson_C": "Gun Damage",
    "WeapTurret_KillTruck_Main_C": "Gun Damage",
    "WeapUMP_C": "Gun Damage",
    "WeapUZI_C": "Gun Damage",
    "WeapVSS_C": "Gun Damage",
    "WeapVector_C": "Gun Damage",
    "WeapWin94_C": "Gun Damage",
    "WeapWinchester_C": "Gun Damage",
    "Weapvz61Skorpion_C": "Gun Damage"
  }
  